setup.py
devserver/__init__.py
devserver/handlers.py
devserver/logger.py
devserver/middleware.py
devserver/models.py
devserver/settings.py
devserver/testcases.py
devserver/tests.py
devserver/management/__init__.py
devserver/management/commands/__init__.py
devserver/management/commands/runserver.py
devserver/modules/__init__.py
devserver/modules/ajax.py
devserver/modules/cache.py
devserver/modules/profile.py
devserver/modules/request.py
devserver/modules/sql.py
devserver/utils/__init__.py
devserver/utils/http.py
devserver/utils/stack.py
devserver/utils/stats.py
devserver/utils/time.py
django_devserver.egg-info/PKG-INFO
django_devserver.egg-info/SOURCES.txt
django_devserver.egg-info/dependency_links.txt
django_devserver.egg-info/top_level.txt